[
{
    "name": "floorGo_test",
    "pngs": [
        {
            "path": "/floorGo/2m2.P.png",
            "frameNum.col":  1,
            "frameNum.row":  1,
            "totalFrameNum": 1,
            "isHaveShadow": false,
            "isPjtSingle": true,
            "isShadowSingle": true,
            "ColliderType": "Nil",
            "subspecies": [
                {
                    "type": "batch",
                    "animLabels": [ "MapEnt_2m2" ],
                    "fstSubIdx": 0,
                    "fstIdx": 0,
                    "idxNums": 1,
                    "name": "idle", "dir": "Mid",
                    "isOpaque": true
                }
            ]
        },
        
        {
            "path": "/floorGo/3m3.P.png",
            "frameNum.col":  1,
            "frameNum.row":  1,
            "totalFrameNum": 1,
            "isHaveShadow": false,
            "isPjtSingle": true,
            "isShadowSingle": true,
            "ColliderType": "Nil",
            "subspecies": [
                {
                    "type": "batch",
                    "animLabels": [ "MapEnt_3m3" ],
                    "fstSubIdx": 0,
                    "fstIdx": 0,
                    "idxNums": 1,
                    "name": "idle", "dir": "Mid",
                    "isOpaque": true
                }
            ]
        },

        {
            "path": "/floorGo/4m4.P.png",
            "frameNum.col":  1,
            "frameNum.row":  1,
            "totalFrameNum": 1,
            "isHaveShadow": false,
            "isPjtSingle": true,
            "isShadowSingle": true,
            "ColliderType": "Nil",
            "subspecies": [
                {
                    "type": "batch",
                    "animLabels": [ "MapEnt_4m4" ],
                    "fstSubIdx": 0,
                    "fstIdx": 0,
                    "idxNums": 1,
                    "name": "idle", "dir": "Mid",
                    "isOpaque": true
                }
            ]
        }

    ]
}


]
